ex4test/__init__.py
ex4test/t1.py
ex4test-1.0.10.dist-info/METADATA
ex4test-1.0.10.dist-info/LICENSE
ex4test-1.0.10.dist-info/WHEEL
ex4test-1.0.10.dist-info/RECORD
